package aprove.verification.oldframework.Bytecode.Parser;

/**
 * All the opcode constants we need.
 * @author cotto
 */
@SuppressWarnings("javadoc")
public class OpcodeConstants {
    static final int NOP = 0x00;
    static final int ACONST_NULL = 0x01;
    static final int ICONST_M1 = 0x02;
    static final int ICONST_0 = 0x03;
    static final int ICONST_5 = 0x08;
    static final int LCONST_0 = 0x09;
    static final int LCONST_1 = 0x0a;
    static final int FCONST_0 = 0x0b;
    static final int FCONST_2 = 0x0d;
    static final int DCONST_0 = 0x0e;
    static final int DCONST_1 = 0x0f;
    static final int BIPUSH = 0x10;
    static final int SIPUSH = 0x11;
    static final int LDC = 0x12;
    static final int LDC2_W = 0x14;
    static final int ILOAD = 0x15;
    static final int LLOAD = 0x16;
    static final int FLOAD = 0x17;
    static final int DLOAD = 0x18;
    static final int ALOAD = 0x19;
    static final int ILOAD_0 = 0x1a;
    static final int ALOAD_3 = 0x2d;
    static final int IALOAD = 0x2e;
    static final int SALOAD = 0x35;
    static final int ISTORE = 0x36;
    static final int LSTORE = 0x37;
    static final int FSTORE = 0x38;
    static final int DSTORE = 0x39;
    static final int ASTORE = 0x3a;
    static final int ISTORE_0 = 0x3b;
    static final int ASTORE_3 = 0x4e;
    static final int IASTORE = 0x4f;
    static final int SASTORE = 0x56;
    static final int POP = 0x57;
    static final int POP2 = 0x58;
    static final int DUP = 0x59;
    static final int DUP_X1 = 0x5a;
    static final int DUP_X2 = 0x5b;
    static final int DUP2 = 0x5c;
    static final int DUP2_X1 = 0x5d;
    static final int DUP2_X2 = 0x5e;
    static final int SWAP = 0x5f;
    static final int IADD = 0x60;
    static final int LADD = 0x61;
    static final int FADD = 0x62;
    static final int DADD = 0x63;
    static final int ISUB = 0x64;
    static final int LSUB = 0x65;
    static final int FSUB = 0x66;
    static final int DSUB = 0x67;
    static final int IMUL = 0x68;
    static final int LMUL = 0x69;
    static final int FMUL = 0x6a;
    static final int DMUL = 0x6b;
    static final int IDIV = 0x6c;
    static final int LDIV = 0x6d;
    static final int FDIV = 0x6e;
    static final int DDIV = 0x6f;
    static final int IREM = 0x70;
    static final int LREM = 0x71;
    static final int FREM = 0x72;
    static final int DREM = 0x73;
    static final int INEG = 0x74;
    static final int LNEG = 0x75;
    static final int FNEG = 0x76;
    static final int DNEG = 0x77;
    static final int ISHL = 0x78;
    static final int LSHL = 0x79;
    static final int ISHR = 0x7a;
    static final int LSHR = 0x7b;
    static final int IUSHR = 0x7c;
    static final int LUSHR = 0x7d;
    static final int IAND = 0x7e;
    static final int LAND = 0x7f;
    static final int IOR = 0x80;
    static final int LOR = 0x81;
    static final int IXOR = 0x82;
    static final int LXOR = 0x83;
    static final int IINC = 0x84;
    static final int I2L = 0x85;
    static final int I2F = 0x86;
    static final int I2D = 0x87;
    static final int L2I = 0x88;
    static final int L2F = 0x89;
    static final int L2D = 0x8a;
    static final int F2I = 0x8b;
    static final int F2L = 0x8c;
    static final int F2D = 0x8d;
    static final int D2I = 0x8e;
    static final int D2L = 0x8f;
    static final int D2F = 0x90;
    static final int I2B = 0x91;
    static final int I2C = 0x92;
    static final int I2S = 0x93;
    static final int LCMP = 0x94;
    static final int FCMPL = 0x95;
    static final int FCMPG = 0x96;
    static final int DCMPL = 0x97;
    static final int DCMPG = 0x98;
    static final int IFEQ = 0x99;
    static final int IFLE = 0x9e;
    static final int IF_ICMPLE = 0xa4;
    static final int IF_ACMPNE = 0xa6;
    static final int GOTO = 0xa7;
    static final int JSR = 0xa8;
    static final int RET = 0xa9;
    static final int TABLESWITCH = 0xaa;
    static final int LOOKUPSWITCH = 0xab;
    static final int IRETURN = 0xac;
    static final int RETURN = 0xb1;
    static final int GETSTATIC = 0xb2;
    static final int PUTFIELD = 0xb5;
    static final int INVOKEVIRTUAL = 0xb6;
    static final int INVOKESPECIAL = 0xb7;
    static final int INVOKESTATIC = 0xb8;
    static final int INVOKEINTERFACE = 0xb9;
    static final int INVOKEDYNAMIC = 0xba;
    static final int NEW = 0xbb;
    static final int NEWARRAY = 0xbc;
    static final int ANEWARRAY = 0xbd;
    static final int ARRAYLENGTH = 0xbe;
    static final int ATHROW = 0xbf;
    static final int CHECKCAST = 0xc0;
    static final int INSTANCEOF = 0xc1;
    static final int MONITORENTER = 0xc2;
    static final int MONITOREXIT = 0xc3;
    static final int WIDE = 0xc4;
    static final int MULTIANEWARRAY = 0xc5;
    static final int IFNULL = 0xc6;
    static final int IFNONNULL = 0xc7;
    static final int GOTO_W = 0xc8;
    static final int JSR_W = 0xc9;
}
